django_statsd/__init__.py
django_statsd/client.py
django_statsd/exception.py
django_statsd/logger.py
django_statsd/middleware.py
django_statsd_prom_exporter-1.0.0.dist-info/LICENSE
django_statsd_prom_exporter-1.0.0.dist-info/METADATA
django_statsd_prom_exporter-1.0.0.dist-info/WHEEL
django_statsd_prom_exporter-1.0.0.dist-info/top_level.txt
django_statsd_prom_exporter-1.0.0.dist-info/RECORD
