Metadata-Version: 2.1
Name: django-statsd-prom-exporter
Version: 1.0.0
Summary: A collection of django middleware to track django + WSGI service metrics accurately via prom/statsd-exporter sidecar + prometheus
Home-page: https://github.com/workindia/django-statsd-prom-exporter
Author: Kshitij Nagvekar
Author-email: kshitij.nagvekar@workindia.in
License: MIT license
Platform: UNKNOWN
Classifier: Development Status :: 5 - Production/Stable
Classifier: License :: OSI Approved :: MIT License
Classifier: Natural Language :: English
Classifier: Programming Language :: Python :: 3
Classifier: Programming Language :: Python :: 3.6
Classifier: Programming Language :: Python :: 3.7
Classifier: Operating System :: OS Independent
Requires-Python: >=3.6
Requires-Dist: django
Requires-Dist: datadog (>=0.42.0)
